dau/__init__.py
dau/core.py
dau_undersampler-0.1.0.dist-info/licenses/LICENSE
dau_undersampler-0.1.0.dist-info/METADATA
dau_undersampler-0.1.0.dist-info/WHEEL
dau_undersampler-0.1.0.dist-info/top_level.txt
dau_undersampler-0.1.0.dist-info/RECORD
