Metadata-Version: 2.4
Name: dau-undersampler
Version: 0.1.0
Summary: Density Aware Undersampling for Imbalanced Data
Home-page: https://github.com/arjunravi26/dau-undersampling
Author: Arjun Ravi
Author-email: arjunravi726@gmail.com
Classifier: Programming Language :: Python :: 3
Classifier: License :: OSI Approved :: MIT License
Classifier: Operating System :: OS Independent
Requires-Python: >=3.7
License-File: LICENSE
Requires-Dist: numpy
Requires-Dist: pandas
Requires-Dist: scikit-learn
Dynamic: author
Dynamic: author-email
Dynamic: classifier
Dynamic: description
Dynamic: description-content-type
Dynamic: home-page
Dynamic: license-file
Dynamic: requires-dist
Dynamic: requires-python
Dynamic: summary
